blade_runner/__init__.py
blade_runner/__main__.py
blade_runner/data/font/small_font.png
blade_runner/data/images/bars.png
blade_runner/data/images/cloud_0.png
blade_runner/data/images/cloud_1.png
blade_runner/data/images/cloud_2.png
blade_runner/data/images/cloud_3.png
blade_runner/data/images/controls.png
blade_runner/data/images/palette.png
blade_runner/data/images/shot.png
blade_runner/data/images/slot.png
blade_runner/data/images/weapon_slot.png
blade_runner/data/images/decor/apples.png
blade_runner/data/images/decor/blueberries.png
blade_runner/data/images/decor/bush.png
blade_runner/data/images/decor/tree.png
blade_runner/data/images/entities/fly/fly_b.png
blade_runner/data/images/entities/fly/fly_f.png
blade_runner/data/images/entities/fly/stand_b.png
blade_runner/data/images/entities/fly/stand_f.png
blade_runner/data/images/entities/player/stand_b.png
blade_runner/data/images/entities/player/stand_f.png
blade_runner/data/images/entities/player/walk_b_0.png
blade_runner/data/images/entities/player/walk_b_1.png
blade_runner/data/images/entities/player/walk_b_2.png
blade_runner/data/images/entities/player/walk_f_0.png
blade_runner/data/images/entities/player/walk_f_1.png
blade_runner/data/images/entities/player/walk_f_2.png
blade_runner/data/images/entities/stomper/stomp_0.png
blade_runner/data/images/entities/stomper/stomp_1.png
blade_runner/data/images/entities/stomper/stomp_2.png
blade_runner/data/images/entities/stomper/stomp_3.png
blade_runner/data/images/entities/stomper/stomp_4.png
blade_runner/data/images/entities/stomper/stomp_5.png
blade_runner/data/images/entities/stomper/stomp_6.png
blade_runner/data/images/entities/tank/main_b_0.png
blade_runner/data/images/entities/tank/main_b_1.png
blade_runner/data/images/entities/tank/main_b_2.png
blade_runner/data/images/entities/tank/main_f_0.png
blade_runner/data/images/entities/tank/main_f_1.png
blade_runner/data/images/entities/tank/main_f_2.png
blade_runner/data/images/items/apples.png
blade_runner-1.1.0.dist-info/METADATA
blade_runner-1.1.0.dist-info/WHEEL
blade_runner-1.1.0.dist-info/entry_points.txt
blade_runner-1.1.0.dist-info/top_level.txt
blade_runner-1.1.0.dist-info/RECORD
