Metadata-Version: 2.1
Name: blade-runner
Version: 1.1.0
Summary: UNKNOWN
Home-page: UNKNOWN
Author: Elisha Hollander
Author-email: UNKNOWN
License: MIT
Platform: UNKNOWN
Classifier: Programming Language :: Python :: 3
Requires-Dist: pygame
